<?xml version="1.0" encoding="utf-8" standalone="yes"?>
<Gesture Name = "eo">
	<Stroke>
		<Point X = "178.5" Y = "442" T = "0" Pressure = "0" />
		<Point X = "178.5" Y = "442" T = "0" Pressure = "0" />
		<Point X = "178.5" Y = "442" T = "0" Pressure = "0" />
		<Point X = "178.5" Y = "442" T = "0" Pressure = "0" />
		<Point X = "178.5" Y = "442" T = "0" Pressure = "0" />
		<Point X = "178.5" Y = "442" T = "0" Pressure = "0" />
		<Point X = "179.5" Y = "442" T = "0" Pressure = "0" />
		<Point X = "179.5" Y = "442" T = "0" Pressure = "0" />
		<Point X = "181.5" Y = "442" T = "0" Pressure = "0" />
		<Point X = "183.5" Y = "442" T = "0" Pressure = "0" />
		<Point X = "184.5" Y = "442" T = "0" Pressure = "0" />
		<Point X = "186.5" Y = "442" T = "0" Pressure = "0" />
		<Point X = "188.5" Y = "442" T = "0" Pressure = "0" />
		<Point X = "190.5" Y = "442" T = "0" Pressure = "0" />
		<Point X = "193.5" Y = "442" T = "0" Pressure = "0" />
		<Point X = "195.5" Y = "442" T = "0" Pressure = "0" />
		<Point X = "197.5" Y = "442" T = "0" Pressure = "0" />
		<Point X = "201.5" Y = "442" T = "0" Pressure = "0" />
		<Point X = "204.5" Y = "442" T = "0" Pressure = "0" />
		<Point X = "206.5" Y = "442" T = "0" Pressure = "0" />
		<Point X = "209.5" Y = "441" T = "0" Pressure = "0" />
		<Point X = "213.5" Y = "441" T = "0" Pressure = "0" />
		<Point X = "215.5" Y = "440" T = "0" Pressure = "0" />
		<Point X = "218.5" Y = "439" T = "0" Pressure = "0" />
		<Point X = "221.5" Y = "439" T = "0" Pressure = "0" />
		<Point X = "224.5" Y = "439" T = "0" Pressure = "0" />
		<Point X = "228.5" Y = "438" T = "0" Pressure = "0" />
		<Point X = "232.5" Y = "437" T = "0" Pressure = "0" />
		<Point X = "235.5" Y = "437" T = "0" Pressure = "0" />
		<Point X = "238.5" Y = "437" T = "0" Pressure = "0" />
		<Point X = "240.5" Y = "437" T = "0" Pressure = "0" />
		<Point X = "242.5" Y = "437" T = "0" Pressure = "0" />
		<Point X = "245.5" Y = "436" T = "0" Pressure = "0" />
		<Point X = "247.5" Y = "436" T = "0" Pressure = "0" />
		<Point X = "250.5" Y = "436" T = "0" Pressure = "0" />
		<Point X = "252.5" Y = "436" T = "0" Pressure = "0" />
		<Point X = "254.5" Y = "436" T = "0" Pressure = "0" />
		<Point X = "256.5" Y = "436" T = "0" Pressure = "0" />
		<Point X = "257.5" Y = "436" T = "0" Pressure = "0" />
		<Point X = "258.5" Y = "436" T = "0" Pressure = "0" />
		<Point X = "259.5" Y = "436" T = "0" Pressure = "0" />
		<Point X = "260.5" Y = "436" T = "0" Pressure = "0" />
		<Point X = "260.5" Y = "436" T = "0" Pressure = "0" />
		<Point X = "260.5" Y = "436" T = "0" Pressure = "0" />
		<Point X = "260.5" Y = "436" T = "0" Pressure = "0" />
		<Point X = "261.5" Y = "436" T = "0" Pressure = "0" />
		<Point X = "261.5" Y = "436" T = "0" Pressure = "0" />
		<Point X = "261.5" Y = "436" T = "0" Pressure = "0" />
		<Point X = "261.5" Y = "436" T = "0" Pressure = "0" />
		<Point X = "261.5" Y = "436" T = "0" Pressure = "0" />
		<Point X = "261.5" Y = "436" T = "0" Pressure = "0" />
		<Point X = "261.5" Y = "436" T = "0" Pressure = "0" />
		<Point X = "261.5" Y = "436" T = "0" Pressure = "0" />
		<Point X = "261.5" Y = "436" T = "0" Pressure = "0" />
		<Point X = "261.5" Y = "436" T = "0" Pressure = "0" />
		<Point X = "261.5" Y = "436" T = "0" Pressure = "0" />
		<Point X = "261.5" Y = "436" T = "0" Pressure = "0" />
		<Point X = "261.5" Y = "436" T = "0" Pressure = "0" />
		<Point X = "261.5" Y = "436" T = "0" Pressure = "0" />
		<Point X = "261.5" Y = "436" T = "0" Pressure = "0" />
	</Stroke>
	<Stroke>
		<Point X = "292.5" Y = "555" T = "0" Pressure = "0" />
		<Point X = "292.5" Y = "555" T = "0" Pressure = "0" />
		<Point X = "292.5" Y = "555" T = "0" Pressure = "0" />
		<Point X = "292.5" Y = "555" T = "0" Pressure = "0" />
		<Point X = "292.5" Y = "555" T = "0" Pressure = "0" />
		<Point X = "292.5" Y = "555" T = "0" Pressure = "0" />
		<Point X = "292.5" Y = "554" T = "0" Pressure = "0" />
		<Point X = "292.5" Y = "551" T = "0" Pressure = "0" />
		<Point X = "292.5" Y = "548" T = "0" Pressure = "0" />
		<Point X = "292.5" Y = "544" T = "0" Pressure = "0" />
		<Point X = "292.5" Y = "537" T = "0" Pressure = "0" />
		<Point X = "291.5" Y = "531" T = "0" Pressure = "0" />
		<Point X = "291.5" Y = "523" T = "0" Pressure = "0" />
		<Point X = "291.5" Y = "513" T = "0" Pressure = "0" />
		<Point X = "290.5" Y = "503" T = "0" Pressure = "0" />
		<Point X = "289.5" Y = "493" T = "0" Pressure = "0" />
		<Point X = "288.5" Y = "476" T = "0" Pressure = "0" />
		<Point X = "287.5" Y = "462" T = "0" Pressure = "0" />
		<Point X = "286.5" Y = "449" T = "0" Pressure = "0" />
		<Point X = "286.5" Y = "431" T = "0" Pressure = "0" />
		<Point X = "284.5" Y = "414" T = "0" Pressure = "0" />
		<Point X = "282.5" Y = "395" T = "0" Pressure = "0" />
		<Point X = "281.5" Y = "380" T = "0" Pressure = "0" />
		<Point X = "280.5" Y = "362" T = "0" Pressure = "0" />
		<Point X = "279.5" Y = "345" T = "0" Pressure = "0" />
		<Point X = "277.5" Y = "331" T = "0" Pressure = "0" />
		<Point X = "276.5" Y = "315" T = "0" Pressure = "0" />
		<Point X = "276.5" Y = "302" T = "0" Pressure = "0" />
		<Point X = "275.5" Y = "288" T = "0" Pressure = "0" />
		<Point X = "274.5" Y = "280" T = "0" Pressure = "0" />
		<Point X = "273.5" Y = "267" T = "0" Pressure = "0" />
		<Point X = "273.5" Y = "260" T = "0" Pressure = "0" />
		<Point X = "272.5" Y = "250" T = "0" Pressure = "0" />
		<Point X = "272.5" Y = "241" T = "0" Pressure = "0" />
		<Point X = "272.5" Y = "235" T = "0" Pressure = "0" />
		<Point X = "272.5" Y = "230" T = "0" Pressure = "0" />
		<Point X = "271.5" Y = "226" T = "0" Pressure = "0" />
		<Point X = "271.5" Y = "223" T = "0" Pressure = "0" />
		<Point X = "271.5" Y = "220" T = "0" Pressure = "0" />
		<Point X = "271.5" Y = "219" T = "0" Pressure = "0" />
		<Point X = "271.5" Y = "217" T = "0" Pressure = "0" />
		<Point X = "271.5" Y = "217" T = "0" Pressure = "0" />
		<Point X = "271.5" Y = "216" T = "0" Pressure = "0" />
		<Point X = "271.5" Y = "216" T = "0" Pressure = "0" />
		<Point X = "271.5" Y = "216" T = "0" Pressure = "0" />
		<Point X = "271.5" Y = "216" T = "0" Pressure = "0" />
		<Point X = "271.5" Y = "216" T = "0" Pressure = "0" />
		<Point X = "271.5" Y = "216" T = "0" Pressure = "0" />
		<Point X = "271.5" Y = "216" T = "0" Pressure = "0" />
		<Point X = "271.5" Y = "216" T = "0" Pressure = "0" />
		<Point X = "271.5" Y = "216" T = "0" Pressure = "0" />
		<Point X = "271.5" Y = "216" T = "0" Pressure = "0" />
		<Point X = "271.5" Y = "216" T = "0" Pressure = "0" />
		<Point X = "271.5" Y = "216" T = "0" Pressure = "0" />
		<Point X = "271.5" Y = "216" T = "0" Pressure = "0" />
		<Point X = "271.5" Y = "216" T = "0" Pressure = "0" />
		<Point X = "271.5" Y = "216" T = "0" Pressure = "0" />
		<Point X = "271.5" Y = "216" T = "0" Pressure = "0" />
		<Point X = "271.5" Y = "216" T = "0" Pressure = "0" />
		<Point X = "271.5" Y = "216" T = "0" Pressure = "0" />
		<Point X = "271.5" Y = "216" T = "0" Pressure = "0" />
		<Point X = "271.5" Y = "216" T = "0" Pressure = "0" />
	</Stroke>
</Gesture>
