<?xml version="1.0" encoding="utf-8" standalone="yes"?>
<Gesture Name = "eu">
	<Stroke>
		<Point X = "96.5" Y = "376" T = "0" Pressure = "0" />
		<Point X = "96.5" Y = "376" T = "0" Pressure = "0" />
		<Point X = "96.5" Y = "376" T = "0" Pressure = "0" />
		<Point X = "96.5" Y = "376" T = "0" Pressure = "0" />
		<Point X = "96.5" Y = "376" T = "0" Pressure = "0" />
		<Point X = "96.5" Y = "376" T = "0" Pressure = "0" />
		<Point X = "96.5" Y = "376" T = "0" Pressure = "0" />
		<Point X = "96.5" Y = "376" T = "0" Pressure = "0" />
		<Point X = "97.5" Y = "377" T = "0" Pressure = "0" />
		<Point X = "99.5" Y = "377" T = "0" Pressure = "0" />
		<Point X = "100.5" Y = "377" T = "0" Pressure = "0" />
		<Point X = "103.5" Y = "377" T = "0" Pressure = "0" />
		<Point X = "105.5" Y = "378" T = "0" Pressure = "0" />
		<Point X = "108.5" Y = "379" T = "0" Pressure = "0" />
		<Point X = "111.5" Y = "379" T = "0" Pressure = "0" />
		<Point X = "115.5" Y = "379" T = "0" Pressure = "0" />
		<Point X = "119.5" Y = "379" T = "0" Pressure = "0" />
		<Point X = "124.5" Y = "380" T = "0" Pressure = "0" />
		<Point X = "131.5" Y = "380" T = "0" Pressure = "0" />
		<Point X = "137.5" Y = "381" T = "0" Pressure = "0" />
		<Point X = "143.5" Y = "381" T = "0" Pressure = "0" />
		<Point X = "149.5" Y = "381" T = "0" Pressure = "0" />
		<Point X = "159.5" Y = "382" T = "0" Pressure = "0" />
		<Point X = "167.5" Y = "382" T = "0" Pressure = "0" />
		<Point X = "177.5" Y = "382" T = "0" Pressure = "0" />
		<Point X = "185.5" Y = "382" T = "0" Pressure = "0" />
		<Point X = "195.5" Y = "382" T = "0" Pressure = "0" />
		<Point X = "207.5" Y = "382" T = "0" Pressure = "0" />
		<Point X = "218.5" Y = "382" T = "0" Pressure = "0" />
		<Point X = "227.5" Y = "382" T = "0" Pressure = "0" />
		<Point X = "235.5" Y = "382" T = "0" Pressure = "0" />
		<Point X = "244.5" Y = "382" T = "0" Pressure = "0" />
		<Point X = "255.5" Y = "382" T = "0" Pressure = "0" />
		<Point X = "267.5" Y = "381" T = "0" Pressure = "0" />
		<Point X = "274.5" Y = "381" T = "0" Pressure = "0" />
		<Point X = "284.5" Y = "380" T = "0" Pressure = "0" />
		<Point X = "294.5" Y = "380" T = "0" Pressure = "0" />
		<Point X = "302.5" Y = "380" T = "0" Pressure = "0" />
		<Point X = "316.5" Y = "379" T = "0" Pressure = "0" />
		<Point X = "325.5" Y = "379" T = "0" Pressure = "0" />
		<Point X = "336.5" Y = "378" T = "0" Pressure = "0" />
		<Point X = "346.5" Y = "377" T = "0" Pressure = "0" />
		<Point X = "353.5" Y = "377" T = "0" Pressure = "0" />
		<Point X = "360.5" Y = "377" T = "0" Pressure = "0" />
		<Point X = "366.5" Y = "377" T = "0" Pressure = "0" />
		<Point X = "370.5" Y = "377" T = "0" Pressure = "0" />
		<Point X = "373.5" Y = "377" T = "0" Pressure = "0" />
		<Point X = "376.5" Y = "377" T = "0" Pressure = "0" />
		<Point X = "379.5" Y = "377" T = "0" Pressure = "0" />
		<Point X = "380.5" Y = "377" T = "0" Pressure = "0" />
		<Point X = "381.5" Y = "377" T = "0" Pressure = "0" />
		<Point X = "382.5" Y = "377" T = "0" Pressure = "0" />
		<Point X = "383.5" Y = "377" T = "0" Pressure = "0" />
		<Point X = "383.5" Y = "377" T = "0" Pressure = "0" />
		<Point X = "383.5" Y = "377" T = "0" Pressure = "0" />
		<Point X = "383.5" Y = "377" T = "0" Pressure = "0" />
		<Point X = "383.5" Y = "377" T = "0" Pressure = "0" />
		<Point X = "383.5" Y = "377" T = "0" Pressure = "0" />
		<Point X = "383.5" Y = "377" T = "0" Pressure = "0" />
		<Point X = "383.5" Y = "377" T = "0" Pressure = "0" />
		<Point X = "383.5" Y = "377" T = "0" Pressure = "0" />
		<Point X = "383.5" Y = "377" T = "0" Pressure = "0" />
		<Point X = "383.5" Y = "377" T = "0" Pressure = "0" />
		<Point X = "383.5" Y = "377" T = "0" Pressure = "0" />
		<Point X = "383.5" Y = "377" T = "0" Pressure = "0" />
		<Point X = "383.5" Y = "377" T = "0" Pressure = "0" />
	</Stroke>
</Gesture>
