<?xml version="1.0" encoding="utf-8" standalone="yes"?>
<Gesture Name = "o">
	<Stroke>
		<Point X = "266.5" Y = "494" T = "0" Pressure = "0" />
		<Point X = "266.5" Y = "494" T = "0" Pressure = "0" />
		<Point X = "266.5" Y = "494" T = "0" Pressure = "0" />
		<Point X = "266.5" Y = "494" T = "0" Pressure = "0" />
		<Point X = "266.5" Y = "494" T = "0" Pressure = "0" />
		<Point X = "266.5" Y = "492" T = "0" Pressure = "0" />
		<Point X = "265.5" Y = "489" T = "0" Pressure = "0" />
		<Point X = "264.5" Y = "485" T = "0" Pressure = "0" />
		<Point X = "264.5" Y = "482" T = "0" Pressure = "0" />
		<Point X = "264.5" Y = "478" T = "0" Pressure = "0" />
		<Point X = "263.5" Y = "474" T = "0" Pressure = "0" />
		<Point X = "262.5" Y = "468" T = "0" Pressure = "0" />
		<Point X = "262.5" Y = "463" T = "0" Pressure = "0" />
		<Point X = "261.5" Y = "458" T = "0" Pressure = "0" />
		<Point X = "260.5" Y = "453" T = "0" Pressure = "0" />
		<Point X = "260.5" Y = "449" T = "0" Pressure = "0" />
		<Point X = "258.5" Y = "443" T = "0" Pressure = "0" />
		<Point X = "258.5" Y = "438" T = "0" Pressure = "0" />
		<Point X = "257.5" Y = "435" T = "0" Pressure = "0" />
		<Point X = "256.5" Y = "432" T = "0" Pressure = "0" />
		<Point X = "256.5" Y = "427" T = "0" Pressure = "0" />
		<Point X = "256.5" Y = "424" T = "0" Pressure = "0" />
		<Point X = "255.5" Y = "421" T = "0" Pressure = "0" />
		<Point X = "255.5" Y = "420" T = "0" Pressure = "0" />
		<Point X = "255.5" Y = "417" T = "0" Pressure = "0" />
		<Point X = "255.5" Y = "415" T = "0" Pressure = "0" />
		<Point X = "255.5" Y = "413" T = "0" Pressure = "0" />
		<Point X = "254.5" Y = "411" T = "0" Pressure = "0" />
		<Point X = "254.5" Y = "409" T = "0" Pressure = "0" />
		<Point X = "254.5" Y = "408" T = "0" Pressure = "0" />
		<Point X = "254.5" Y = "407" T = "0" Pressure = "0" />
		<Point X = "254.5" Y = "406" T = "0" Pressure = "0" />
		<Point X = "254.5" Y = "405" T = "0" Pressure = "0" />
		<Point X = "254.5" Y = "405" T = "0" Pressure = "0" />
		<Point X = "254.5" Y = "405" T = "0" Pressure = "0" />
		<Point X = "254.5" Y = "405" T = "0" Pressure = "0" />
		<Point X = "254.5" Y = "405" T = "0" Pressure = "0" />
		<Point X = "254.5" Y = "404" T = "0" Pressure = "0" />
		<Point X = "254.5" Y = "404" T = "0" Pressure = "0" />
		<Point X = "254.5" Y = "404" T = "0" Pressure = "0" />
		<Point X = "254.5" Y = "404" T = "0" Pressure = "0" />
		<Point X = "254.5" Y = "404" T = "0" Pressure = "0" />
		<Point X = "254.5" Y = "404" T = "0" Pressure = "0" />
		<Point X = "254.5" Y = "404" T = "0" Pressure = "0" />
		<Point X = "254.5" Y = "404" T = "0" Pressure = "0" />
		<Point X = "254.5" Y = "404" T = "0" Pressure = "0" />
		<Point X = "254.5" Y = "404" T = "0" Pressure = "0" />
		<Point X = "254.5" Y = "404" T = "0" Pressure = "0" />
		<Point X = "254.5" Y = "404" T = "0" Pressure = "0" />
		<Point X = "254.5" Y = "404" T = "0" Pressure = "0" />
		<Point X = "254.5" Y = "404" T = "0" Pressure = "0" />
		<Point X = "254.5" Y = "404" T = "0" Pressure = "0" />
		<Point X = "254.5" Y = "404" T = "0" Pressure = "0" />
		<Point X = "254.5" Y = "404" T = "0" Pressure = "0" />
		<Point X = "254.5" Y = "404" T = "0" Pressure = "0" />
		<Point X = "254.5" Y = "404" T = "0" Pressure = "0" />
		<Point X = "254.5" Y = "404" T = "0" Pressure = "0" />
		<Point X = "254.5" Y = "404" T = "0" Pressure = "0" />
		<Point X = "254.5" Y = "404" T = "0" Pressure = "0" />
		<Point X = "254.5" Y = "404" T = "0" Pressure = "0" />
		<Point X = "254.5" Y = "404" T = "0" Pressure = "0" />
		<Point X = "254.5" Y = "404" T = "0" Pressure = "0" />
		<Point X = "254.5" Y = "404" T = "0" Pressure = "0" />
		<Point X = "254.5" Y = "404" T = "0" Pressure = "0" />
		<Point X = "254.5" Y = "404" T = "0" Pressure = "0" />
		<Point X = "254.5" Y = "404" T = "0" Pressure = "0" />
		<Point X = "254.5" Y = "404" T = "0" Pressure = "0" />
		<Point X = "254.5" Y = "404" T = "0" Pressure = "0" />
		<Point X = "254.5" Y = "404" T = "0" Pressure = "0" />
		<Point X = "254.5" Y = "404" T = "0" Pressure = "0" />
		<Point X = "254.5" Y = "404" T = "0" Pressure = "0" />
		<Point X = "254.5" Y = "404" T = "0" Pressure = "0" />
		<Point X = "254.5" Y = "404" T = "0" Pressure = "0" />
		<Point X = "254.5" Y = "404" T = "0" Pressure = "0" />
		<Point X = "254.5" Y = "404" T = "0" Pressure = "0" />
	</Stroke>
	<Stroke>
		<Point X = "96.5" Y = "399" T = "0" Pressure = "0" />
		<Point X = "96.5" Y = "399" T = "0" Pressure = "0" />
		<Point X = "96.5" Y = "399" T = "0" Pressure = "0" />
		<Point X = "96.5" Y = "399" T = "0" Pressure = "0" />
		<Point X = "96.5" Y = "399" T = "0" Pressure = "0" />
		<Point X = "96.5" Y = "399" T = "0" Pressure = "0" />
		<Point X = "96.5" Y = "399" T = "0" Pressure = "0" />
		<Point X = "96.5" Y = "399" T = "0" Pressure = "0" />
		<Point X = "96.5" Y = "399" T = "0" Pressure = "0" />
		<Point X = "97.5" Y = "399" T = "0" Pressure = "0" />
		<Point X = "98.5" Y = "399" T = "0" Pressure = "0" />
		<Point X = "100.5" Y = "399" T = "0" Pressure = "0" />
		<Point X = "102.5" Y = "399" T = "0" Pressure = "0" />
		<Point X = "105.5" Y = "400" T = "0" Pressure = "0" />
		<Point X = "108.5" Y = "400" T = "0" Pressure = "0" />
		<Point X = "111.5" Y = "400" T = "0" Pressure = "0" />
		<Point X = "116.5" Y = "400" T = "0" Pressure = "0" />
		<Point X = "122.5" Y = "400" T = "0" Pressure = "0" />
		<Point X = "128.5" Y = "400" T = "0" Pressure = "0" />
		<Point X = "133.5" Y = "400" T = "0" Pressure = "0" />
		<Point X = "140.5" Y = "400" T = "0" Pressure = "0" />
		<Point X = "150.5" Y = "400" T = "0" Pressure = "0" />
		<Point X = "159.5" Y = "400" T = "0" Pressure = "0" />
		<Point X = "167.5" Y = "400" T = "0" Pressure = "0" />
		<Point X = "180.5" Y = "400" T = "0" Pressure = "0" />
		<Point X = "189.5" Y = "400" T = "0" Pressure = "0" />
		<Point X = "205.5" Y = "399" T = "0" Pressure = "0" />
		<Point X = "216.5" Y = "398" T = "0" Pressure = "0" />
		<Point X = "229.5" Y = "397" T = "0" Pressure = "0" />
		<Point X = "243.5" Y = "395" T = "0" Pressure = "0" />
		<Point X = "256.5" Y = "395" T = "0" Pressure = "0" />
		<Point X = "268.5" Y = "394" T = "0" Pressure = "0" />
		<Point X = "280.5" Y = "393" T = "0" Pressure = "0" />
		<Point X = "296.5" Y = "392" T = "0" Pressure = "0" />
		<Point X = "308.5" Y = "391" T = "0" Pressure = "0" />
		<Point X = "318.5" Y = "390" T = "0" Pressure = "0" />
		<Point X = "331.5" Y = "390" T = "0" Pressure = "0" />
		<Point X = "341.5" Y = "389" T = "0" Pressure = "0" />
		<Point X = "352.5" Y = "389" T = "0" Pressure = "0" />
		<Point X = "361.5" Y = "388" T = "0" Pressure = "0" />
		<Point X = "371.5" Y = "388" T = "0" Pressure = "0" />
		<Point X = "382.5" Y = "387" T = "0" Pressure = "0" />
		<Point X = "391.5" Y = "387" T = "0" Pressure = "0" />
		<Point X = "404.5" Y = "387" T = "0" Pressure = "0" />
		<Point X = "414.5" Y = "387" T = "0" Pressure = "0" />
		<Point X = "420.5" Y = "387" T = "0" Pressure = "0" />
		<Point X = "426.5" Y = "387" T = "0" Pressure = "0" />
		<Point X = "431.5" Y = "387" T = "0" Pressure = "0" />
		<Point X = "435.5" Y = "387" T = "0" Pressure = "0" />
		<Point X = "441.5" Y = "387" T = "0" Pressure = "0" />
		<Point X = "444.5" Y = "387" T = "0" Pressure = "0" />
		<Point X = "446.5" Y = "387" T = "0" Pressure = "0" />
		<Point X = "448.5" Y = "387" T = "0" Pressure = "0" />
		<Point X = "449.5" Y = "387" T = "0" Pressure = "0" />
		<Point X = "450.5" Y = "387" T = "0" Pressure = "0" />
		<Point X = "451.5" Y = "387" T = "0" Pressure = "0" />
		<Point X = "451.5" Y = "387" T = "0" Pressure = "0" />
		<Point X = "451.5" Y = "387" T = "0" Pressure = "0" />
		<Point X = "451.5" Y = "387" T = "0" Pressure = "0" />
		<Point X = "451.5" Y = "387" T = "0" Pressure = "0" />
		<Point X = "451.5" Y = "387" T = "0" Pressure = "0" />
		<Point X = "451.5" Y = "387" T = "0" Pressure = "0" />
		<Point X = "451.5" Y = "387" T = "0" Pressure = "0" />
		<Point X = "451.5" Y = "387" T = "0" Pressure = "0" />
		<Point X = "451.5" Y = "387" T = "0" Pressure = "0" />
		<Point X = "451.5" Y = "387" T = "0" Pressure = "0" />
		<Point X = "451.5" Y = "387" T = "0" Pressure = "0" />
	</Stroke>
</Gesture>
